algoalpha-0.0.1.dist-info/METADATA
algoalpha-0.0.1.dist-info/WHEEL
algoalpha/__init__.py
algoalpha/_lib.abi3.so
algoalpha/adaptive_schaff_trend_cycle.py
algoalpha/amazing_oscillator.py
algoalpha/exponential_trend.py
algoalpha/intrinsics.py
algoalpha/supertrended_rsi.py
algoalpha/triple_smoothed_signals.py
algoalpha-0.0.1.dist-info/RECORD
