Metadata-Version: 2.4
Name: algoalpha
Version: 0.0.1
Requires-Dist: qpace>=0.1.0
Summary: 
Keywords: 
Project-URL: Homepage, https://qpace.dev
Project-URL: Repository, https://github.com/nersent/qpace
